Metadata-Version: 2.1
Name: tgs11
Version: 0.1.0
Summary: First tea package
Home-page: https://github.com/ganisacik/tgs11
Author: ganisacik
Author-email: senin-email@example.com
License: UNKNOWN
Project-URL: Source, https://github.com/ganisacik/tgs11
Platform: UNKNOWN
